skellyai/__init__.py
skellyai/train_transformer.py
skellyai/get_multi_labels/__init__.py
skellyai/get_multi_labels/get_multi_labels.py
skellyai/perform_inference/__init__.py
skellyai/perform_inference/get_probs.py
skellyai/perform_inference/get_probs_mult_keywords.py
skellyai/perform_inference/test.py
skellyai-0.2.5.dist-info/METADATA
skellyai-0.2.5.dist-info/WHEEL
skellyai-0.2.5.dist-info/top_level.txt
skellyai-0.2.5.dist-info/RECORD
