Metadata-Version: 2.1
Name: skellyai
Version: 0.2.5
Summary: generated labeled data
Author: Ben Nicholl
Author-email: ben.nicholl66@gmail.com
License: BSD 2-clause
Classifier: Development Status :: 1 - Planning
Classifier: Intended Audience :: Science/Research
Classifier: License :: OSI Approved :: BSD License
Classifier: Operating System :: POSIX :: Linux
Classifier: Programming Language :: Python :: 3
Requires-Dist: pandas (==1.4.4)
Requires-Dist: sagemaker (==2.173.0)
